YODA Project code_V2/src/Parameter.v
// =========================================================================
// Practical 4: StarCore-1 — Single-Cycle Processor in Verilog
// =========================================================================
//
// GROUP NUMBER: 14
//
// MEMBERS:
//   - May Yuan-Klitzner, YNKMAY001
//   - Colby Skirving, SKRCOL001
//   -Sandakahle Bhengu, BHNSAN010

// File        : Parameter.v
// Description : Shared compile-time parameters used across all modules.
//               Include this file at the top of every .v file:
//                   `include "../src/Parameter.v"
// =============================================================================

`ifndef PARAMETER_H_
`define PARAMETER_H_

// ---------------------------------------------------------------------------
// Memory dimensions
// ---------------------------------------------------------------------------
`define COL     16          // Data/instruction word width (bits)
`define ROW_I   16          // Instruction memory depth (words, 16 x 16-bit)
`define ROW_D    10          // Data memory depth (words,  8 x 16-bit)

// ---------------------------------------------------------------------------
// Simulation control
// Increase SIM_TIME if your test program needs more clock cycles to complete.
// At 10 ns per clock (100 MHz) each #10 is one half-period; 320 ns = 16 cycles.
// ---------------------------------------------------------------------------
`define SIM_TIME  #80       // Total simulation time for integration testbench

// ---------------------------------------------------------------------------
// Output file for data-memory dump (used in DataMemory.v $fmonitor)
// ---------------------------------------------------------------------------
`define DMEM_LOG  "./waves/dmem_log.txt"

`endif  // PARAMETER_H_

YODA Project code_V2/src/ALU_Control.v
// =========================================================================
// Practical 4: StarCore-1 — Single-Cycle Processor in Verilog
// =========================================================================
//
// GROUP NUMBER: 14
//
// MEMBERS:
//   - May Yuan-Klitzner, YNKMAY001
//   - Colby Skirving, SKRCOL001
//
// File        : ALU_Control.v
// Description : ALU Control Unit — Extended for FPC-16 Fixed-Point Core.
//               Maps the 2-bit ALUOp signal (from the Main Control Unit) and
//               the 4-bit instruction opcode to the 4-bit ALUcnt signal that
//               drives the ALU's operation select input.
//               Extended from 3-bit to 4-bit ALU_Cnt to support two new
//               fixed-point instructions: FPMUL (opcode 1110) and FPDIV (1111).
//               This is a purely combinational module.
// =============================================================================

`timescale 1ns / 1ps
`include "../src/Parameter.v"

module ALU_Control (
    input  [1:0] ALUOp,         // From ControlUnit:
                                //   2'b10 = memory access (always ADD for address)
                                //   2'b01 = branch      (always SUB for comparison)
                                //   2'b00 = R-type      (decode from opcode)
    input  [3:0] Opcode,        // Instruction opcode field [15:12]
    output reg [3:0] ALU_Cnt    // Extended: was [2:0], now [3:0] for FPC-16
);

    // -------------------------------------------------------------------------
    // Concatenate ALUOp and Opcode into a single 6-bit control word
    // -------------------------------------------------------------------------
    wire [5:0] control_in;
    assign control_in = {ALUOp, Opcode};

    // -------------------------------------------------------------------------
    // casex truth table:
    //
    // control_in | ALU_Cnt | Operation   | Instruction
    // -----------+---------+-------------+------------------
    // 6'b10xxxx  |  4'b0000 | ADD        | LD, ST
    // 6'b01xxxx  |  4'b0001 | SUB        | BEQ, BNE
    // 6'b000010  |  4'b0000 | ADD        | ADD  (also FPADD — no new hardware)
    // 6'b000011  |  4'b0001 | SUB        | SUB  (also FPSUB — no new hardware)
    // 6'b000100  |  4'b0010 | INV        | INV
    // 6'b000101  |  4'b0011 | SHL        | SHL
    // 6'b000110  |  4'b0100 | SHR        | SHR
    // 6'b000111  |  4'b0101 | AND        | AND
    // 6'b001000  |  4'b0110 | OR         | OR
    // 6'b001001  |  4'b0111 | SLT        | SLT
    // 6'b001110  |  4'b1000 | FPMUL      | FPMUL (NEW — FPC-16)
    // 6'b001111  |  4'b1001 | FPDIV      | FPDIV (NEW — FPC-16)
    // default    |  4'b0000 | ADD (safe) | reserved / undefined
    // -------------------------------------------------------------------------
    always @(*) begin
        casex (control_in)
            // Existing operations — unchanged
            6'b10xxxx : ALU_Cnt = 4'b0000; // ADD — LD/ST address calculation
            6'b01xxxx : ALU_Cnt = 4'b0001; // SUB — branch comparison
            6'b000010 : ALU_Cnt = 4'b0000; // ADD (reused for FPADD)
            6'b000011 : ALU_Cnt = 4'b0001; // SUB (reused for FPSUB)
            6'b000100 : ALU_Cnt = 4'b0010; // INV
            6'b000101 : ALU_Cnt = 4'b0011; // SHL
            6'b000110 : ALU_Cnt = 4'b0100; // SHR
            6'b000111 : ALU_Cnt = 4'b0101; // AND
            6'b001000 : ALU_Cnt = 4'b0110; // OR
            6'b001001 : ALU_Cnt = 4'b0111; // SLT
            // New FPC-16 fixed-point operations
            6'b001110 : ALU_Cnt = 4'b1000; // FPMUL — Q8.8 multiply
            6'b001111 : ALU_Cnt = 4'b1001; // FPDIV — Q8.8 divide
            default   : ALU_Cnt = 4'b0000; // Safe fallback
        endcase
    end

endmodule

YODA Project code_V2/tb/ALU_Control_tb.v
// =============================================================================
// EEE4120F Practical 4 — StarCore-1 Processor
// File        : ALU_Control_tb.v
// Description : Testbench for the ALU Control Unit — Extended for FPC-16.
//               Drives every row of the ALU control truth table and verifies
//               the 4-bit ALUcnt output (extended from 3-bit for FPC-16).
//               New test cases added for FPMUL (opcode 1110) and FPDIV (1111).
//
// Run:
//   iverilog -Wall -I ../src -o ../build/ac_sim ../src/ALU_Control.v ALU_Control_tb.v
//   cd ../test && ../build/ac_sim
//   gtkwave ../waves/ac_tb.vcd &
// =============================================================================

`timescale 1ns / 1ps
`include "../src/Parameter.v"

module ALU_Control_tb;

    reg  [1:0] ALUOp;
    reg  [3:0] Opcode;
    wire [3:0] ALU_Cnt;   // Extended: was [2:0], now [3:0] for FPC-16

    ALU_Control uut (
        .ALUOp   (ALUOp),
        .Opcode  (Opcode),
        .ALU_Cnt (ALU_Cnt)
    );

    initial begin
        $dumpfile("../waves/ac_tb.vcd");
        $dumpvars(0, ALU_Control_tb);
    end

    integer fail_count;
    integer test_id;

    // -------------------------------------------------------------------------
    // check_cnt task — extended to 4-bit for FPC-16
    // -------------------------------------------------------------------------
    task check_cnt;
        input [3:0] got;       // Extended: was [2:0], now [3:0]
        input [3:0] expected;  // Extended: was [2:0], now [3:0]
        input [63:0] id;
        begin
            if (got !== expected) begin
                $display("FAIL [T%0d]: ALU_Cnt = %b, expected = %b", id, got, expected);
                fail_count = fail_count + 1;
            end else
                $display("PASS [T%0d]: ALU_Cnt = %b", id, got);
        end
    endtask

    initial begin
        fail_count = 0;
        test_id    = 1;
        $display("=== ALU_Control Testbench ===");

        // ------------------------------------------------------------------
        // ALUOp = 10 (memory access) — always ADD regardless of opcode
        // ------------------------------------------------------------------
        $display("--- ALUOp=10: all opcodes should map to ADD (0000) ---");

        ALUOp = 2'b10; Opcode = 4'h0; #10;
        check_cnt(ALU_Cnt, 4'b0000, test_id); test_id = test_id + 1;

        ALUOp = 2'b10; Opcode = 4'h5; #10;
        check_cnt(ALU_Cnt, 4'b0000, test_id); test_id = test_id + 1;

        ALUOp = 2'b10; Opcode = 4'hF; #10;
        check_cnt(ALU_Cnt, 4'b0000, test_id); test_id = test_id + 1;

        // ------------------------------------------------------------------
        // ALUOp = 01 (branch) — always SUB regardless of opcode
        // ------------------------------------------------------------------
        $display("--- ALUOp=01: all opcodes should map to SUB (0001) ---");

        ALUOp = 2'b01; Opcode = 4'h0; #10;
        check_cnt(ALU_Cnt, 4'b0001, test_id); test_id = test_id + 1;

        ALUOp = 2'b01; Opcode = 4'hB; #10;
        check_cnt(ALU_Cnt, 4'b0001, test_id); test_id = test_id + 1;

        ALUOp = 2'b01; Opcode = 4'hF; #10;
        check_cnt(ALU_Cnt, 4'b0001, test_id); test_id = test_id + 1;

        // ------------------------------------------------------------------
        // ALUOp = 00 (R-type) — decode from opcode
        // ------------------------------------------------------------------
        $display("--- ALUOp=00: decode per opcode ---");

        ALUOp = 2'b00; Opcode = 4'h2; #10;  // ADD
        check_cnt(ALU_Cnt, 4'b0000, test_id); test_id = test_id + 1;

        ALUOp = 2'b00; Opcode = 4'h3; #10;  // SUB
        check_cnt(ALU_Cnt, 4'b0001, test_id); test_id = test_id + 1;

        ALUOp = 2'b00; Opcode = 4'h4; #10;  // INV
        check_cnt(ALU_Cnt, 4'b0010, test_id); test_id = test_id + 1;

        ALUOp = 2'b00; Opcode = 4'h5; #10;  // SHL
        check_cnt(ALU_Cnt, 4'b0011, test_id); test_id = test_id + 1;

        ALUOp = 2'b00; Opcode = 4'h6; #10;  // SHR
        check_cnt(ALU_Cnt, 4'b0100, test_id); test_id = test_id + 1;

        ALUOp = 2'b00; Opcode = 4'h7; #10;  // AND
        check_cnt(ALU_Cnt, 4'b0101, test_id); test_id = test_id + 1;

        ALUOp = 2'b00; Opcode = 4'h8; #10;  // OR
        check_cnt(ALU_Cnt, 4'b0110, test_id); test_id = test_id + 1;

        ALUOp = 2'b00; Opcode = 4'h9; #10;  // SLT
        check_cnt(ALU_Cnt, 4'b0111, test_id); test_id = test_id + 1;

        // ------------------------------------------------------------------
        // Default case — undefined opcodes should default to ADD (0000)
        // Note: opcode 4'hF is now FPDIV, so use 4'hA as undefined
        // ------------------------------------------------------------------
        $display("--- Default (ALUOp=00, undefined opcode) -> ADD (0000) ---");

        ALUOp = 2'b00; Opcode = 4'hA; #10;  // reserved NOP — defaults to ADD
        check_cnt(ALU_Cnt, 4'b0000, test_id); test_id = test_id + 1;

        ALUOp = 2'b00; Opcode = 4'hD; #10;  // JMP opcode — defaults to ADD
        check_cnt(ALU_Cnt, 4'b0000, test_id); test_id = test_id + 1;

        // ------------------------------------------------------------------
        // FPC-16 New Fixed-Point Instructions
        // FPMUL (opcode 1110 = 4'hE) -> ALU_Cnt = 4'b1000
        // FPDIV (opcode 1111 = 4'hF) -> ALU_Cnt = 4'b1001
        // ------------------------------------------------------------------
        $display("--- FPC-16: FPMUL and FPDIV opcodes ---");

        ALUOp = 2'b00; Opcode = 4'hE; #10;  // FPMUL — Q8.8 multiply
        check_cnt(ALU_Cnt, 4'b1000, test_id); test_id = test_id + 1;

        ALUOp = 2'b00; Opcode = 4'hF; #10;  // FPDIV — Q8.8 divide
        check_cnt(ALU_Cnt, 4'b1001, test_id); test_id = test_id + 1;

        // ------------------------------------------------------------------
        // Summary
        // ------------------------------------------------------------------
        $display("");
        if (fail_count == 0)
            $display("=== ALL %0d TESTS PASSED ===", test_id - 1);
        else
            $display("=== %0d / %0d TESTS FAILED ===", fail_count, test_id - 1);
        $finish;
    end

endmodule

YODA Project code_V2/waves/ac_tb.vcd
$date
	Thu Apr 30 18:55:57 2026
$end
$version
	Icarus Verilog
$end
$timescale
	1ps
$end
$scope module ALU_Control_tb $end
$var wire 4 ! ALU_Cnt [3:0] $end
$var reg 2 " ALUOp [1:0] $end
$var reg 4 # Opcode [3:0] $end
$var integer 32 $ fail_count [31:0] $end
$var integer 32 % test_id [31:0] $end
$scope module uut $end
$var wire 2 & ALUOp [1:0] $end
$var wire 4 ' Opcode [3:0] $end
$var wire 6 ( control_in [5:0] $end
$var reg 4 ) ALU_Cnt [3:0] $end
$upscope $end
$scope task check_cnt $end
$var reg 4 * expected [3:0] $end
$var reg 4 + got [3:0] $end
$var reg 64 , id [63:0] $end
$upscope $end
$upscope $end
$enddefinitions $end
$comment Show the parameter values. $end
$dumpall
$end
#0
$dumpvars
bx ,
bx +
bx *
b0 )
b100000 (
b0 '
b10 &
b1 %
b0 $
b0 #
b10 "
b0 !
$end
#10000
b100101 (
b101 #
b101 '
b10 %
b1 ,
b0 *
b0 +
#20000
b101111 (
b1111 #
b1111 '
b11 %
b10 ,
#30000
b1 !
b1 )
b0 #
b0 '
b10000 (
b1 "
b1 &
b100 %
b11 ,
#40000
b11011 (
b1011 #
b1011 '
b101 %
b100 ,
b1 *
b1 +
#50000
b11111 (
b1111 #
b1111 '
b110 %
b101 ,
#60000
b0 !
b0 )
b10 #
b10 '
b10 (
b0 "
b0 &
b111 %
b110 ,
#70000
b1 !
b1 )
b11 (
b11 #
b11 '
b1000 %
b111 ,
b0 *
b0 +
#80000
b10 !
b10 )
b100 (
b100 #
b100 '
b1001 %
b1000 ,
b1 *
b1 +
#90000
b11 !
b11 )
b101 (
b101 #
b101 '
b1010 %
b1001 ,
b10 *
b10 +
#100000
b100 !
b100 )
b110 (
b110 #
b110 '
b1011 %
b1010 ,
b11 *
b11 +
#110000
b101 !
b101 )
b111 (
b111 #
b111 '
b1100 %
b1011 ,
b100 *
b100 +
#120000
b110 !
b110 )
b1000 (
b1000 #
b1000 '
b1101 %
b1100 ,
b101 *
b101 +
#130000
b111 !
b111 )
b1001 (
b1001 #
b1001 '
b1110 %
b1101 ,
b110 *
b110 +
#140000
b0 !
b0 )
b1010 (
b1010 #
b1010 '
b1111 %
b1110 ,
b111 *
b111 +
#150000
b1101 (
b1101 #
b1101 '
b10000 %
b1111 ,
b0 *
b0 +
#160000
b1000 !
b1000 )
b1110 (
b1110 #
b1110 '
b10001 %
b10000 ,
#170000
b1001 !
b1001 )
b1111 (
b1111 #
b1111 '
b10010 %
b10001 ,
b1000 *
b1000 +
#180000
b10011 %
b10010 ,
b1001 *
b1001 +
